json2xls/__init__.py
json2xls/json2xls.py
json2xls-1.0.0.dist-info/METADATA
json2xls-1.0.0.dist-info/WHEEL
json2xls-1.0.0.dist-info/entry_points.txt
json2xls-1.0.0.dist-info/top_level.txt
json2xls-1.0.0.dist-info/RECORD
