Metadata-Version: 2.1
Name: json2xls
Version: 1.0.0
Summary: generate excel by json
Home-page: https://github.com/axiaoxin/json2xls
Author: axiaoxin
Author-email: 254606826@qq.com
License: BSD
Keywords: json2xls
Platform: UNKNOWN
Classifier: Development Status :: 2 - Pre-Alpha
Classifier: Intended Audience :: Developers
Classifier: License :: OSI Approved :: BSD License
Classifier: Natural Language :: English
Classifier: Programming Language :: Python :: 2.7
Classifier: Programming Language :: Python :: 3.6
Requires-Dist: click
Requires-Dist: requests
Requires-Dist: xlwt
